inspektor/__init__.py
inspektor/indent.py
inspektor/license.py
inspektor/lint.py
inspektor/patch.py
inspektor/path.py
inspektor/style.py
inspektor/cli/__init__.py
inspektor/cli/app.py
inspektor/commands/__init__.py
inspektor/commands/checkall.py
inspektor/commands/github.py
inspektor/commands/indent.py
inspektor/commands/license.py
inspektor/commands/lint.py
inspektor/commands/style.py
inspektor/utils/__init__.py
inspektor/utils/data_structures.py
inspektor/utils/download.py
inspektor/utils/exceptions.py
inspektor/utils/process.py
inspektor/utils/stacktrace.py
inspektor/utils/vcs.py
inspektor-0.5.3.dist-info/LICENSE
inspektor-0.5.3.dist-info/METADATA
inspektor-0.5.3.dist-info/WHEEL
inspektor-0.5.3.dist-info/entry_points.txt
inspektor-0.5.3.dist-info/namespace_packages.txt
inspektor-0.5.3.dist-info/top_level.txt
inspektor-0.5.3.dist-info/RECORD
