Metadata-Version: 2.1
Name: inspektor
Version: 0.5.3
Summary: Inspektor python code checker and fixer
Home-page: https://github.com/avocado-framework/inspektor
Author: Lucas Meneghel Rodrigues
Author-email: lookkas@gmail.com
License: UNKNOWN
Download-URL: https://github.com/avocado-framework/inspektor/tarball/master
Platform: Any
Classifier: Development Status :: 3 - Alpha
Classifier: License :: OSI Approved :: GNU General Public License v2 or later (GPLv2+)
Classifier: Programming Language :: Python
Classifier: Programming Language :: Python :: 2
Classifier: Programming Language :: Python :: 2.7
Classifier: Programming Language :: Python :: 3
Classifier: Programming Language :: Python :: 3.6
Classifier: Intended Audience :: Developers
Classifier: Environment :: Console
License-File: LICENSE
Requires-Dist: six
Requires-Dist: pycodestyle
Requires-Dist: pylint
Requires-Dist: cliff
